<view:view xmlns:view="http://www.alfresco.org/view/repository/1.0"
           xmlns:cm="http://www.alfresco.org/model/content/1.0"
           xmlns:sys="http://www.alfresco.org/model/system/1.0"
           xmlns:app="http://www.alfresco.org/model/application/1.0"
          xmlns:usr="http://www.alfresco.org/model/user/1.0">
	   <usr:user view:childName="usr:user">
                    <usr:username>fredb</usr:username>
                    <usr:password>fredb</usr:password>   
                    <usr:enabled>true</usr:enabled>
                    <usr:accountExpires>false</usr:accountExpires>   
                    <usr:credentialsExpire>false</usr:credentialsExpire>
                     usr:accountLocked>false
                    </usr:accountLocked>
                    <sys:node-uuid>4489977c-25b4-4980-ab2e-6d6307472bfa
                    </sys:node-uuid>
          </usr:user>
          <usr:user view:childName="usr:user">
                        <usr:username>sues</usr:username>
                        <usr:password>sues</usr:password>   
                        <usr:enabled>true</usr:enabled>
                        <usr:accountExpires>false</usr:accountExpires>
                        <usr:credentialsExpire>false
                        </usr:credentialsExpire>
                        <usr:accountLocked>false</usr:accountLocked>
                        <sys:node-uuid>4489977c-25b4-4980-ab2e-6d6307472bfb
                        </sys:node-uuid>
                        </usr:user> 
</view:view>
